hs_ocr_lib_test/__init__.py
hs_ocr_lib_test/test.py
testprojectrajlaxmi-0.0.1.dist-info/METADATA
testprojectrajlaxmi-0.0.1.dist-info/WHEEL
testprojectrajlaxmi-0.0.1.dist-info/top_level.txt
testprojectrajlaxmi-0.0.1.dist-info/RECORD
